BOFdat/__init__.py
BOFdat/step1.py
BOFdat/step2.py
BOFdat/step3.py
BOFdat/core/__init__.py
BOFdat/core/chose_metab.py
BOFdat/core/coenzymes_and_ions.py
BOFdat/core/dna.py
BOFdat/core/group_end_goals.py
BOFdat/core/initial_population.py
BOFdat/core/lipid.py
BOFdat/core/maintenance.py
BOFdat/core/metab_end_goals.py
BOFdat/core/metabolite.py
BOFdat/core/protein.py
BOFdat/core/qualitative.py
BOFdat/core/rna.py
BOFdat/data/BIOMASS_universal_components.csv
BOFdat/data/Ecoli_DNA.fna
BOFdat/data/Ecoli_K12_MG1655.gbff
BOFdat/data/iML1515.json
BOFdat/data/lipidomic_abundances.csv
BOFdat/data/lipidomic_conversion.csv
BOFdat/data/maintenance.csv
BOFdat/data/metabolites_to_add.csv
BOFdat/data/metabolomic_abundances.csv
BOFdat/data/metabolomic_conversion.csv
BOFdat/data/new_lipidomic_abundances.csv
BOFdat/data/proteomic.csv
BOFdat/data/transcriptomic.csv
BOFdat/util/__init__.py
BOFdat/util/dijkstra.py
BOFdat/util/update.py
BOFdat-0.1.7.dist-info/LICENSE
BOFdat-0.1.7.dist-info/METADATA
BOFdat-0.1.7.dist-info/WHEEL
BOFdat-0.1.7.dist-info/top_level.txt
BOFdat-0.1.7.dist-info/RECORD
